flask_orientdb.py
setup.cfg
setup.py
Flask_OrientDB.egg-info/PKG-INFO
Flask_OrientDB.egg-info/SOURCES.txt
Flask_OrientDB.egg-info/dependency_links.txt
Flask_OrientDB.egg-info/not-zip-safe
Flask_OrientDB.egg-info/pbr.json
Flask_OrientDB.egg-info/requires.txt
Flask_OrientDB.egg-info/top_level.txt