Metadata-Version: 1.1
Name: Flask-OrientDB
Version: 0.1
Summary: A Flask extension for using OrientDB with Flask
Home-page: http://github.com/calthoff/flask-orientdb
Author: Cory Althoff
Author-email: coryedwardalthoff@gmail.com
License: BSD
Platform: any
Classifier: Development Status :: 4 - Beta
Classifier: Environment :: Web Environment
Classifier: Intended Audience :: Developers
Classifier: License :: OSI Approved :: BSD License
Classifier: Operating System :: OS Independent
Classifier: Programming Language :: Python
Classifier: Topic :: Internet :: WWW/HTTP :: Dynamic Content
Classifier: Topic :: Software Development :: Libraries :: Python Modules
